liblaf/cherries/__init__.py
liblaf/cherries/__init__.pyi
liblaf/cherries/_version.py
liblaf/cherries/_version.pyi
liblaf/cherries/py.typed
liblaf/cherries/_main/__init__.py
liblaf/cherries/_main/__init__.pyi
liblaf/cherries/_main/_end.py
liblaf/cherries/_main/_main.py
liblaf/cherries/_main/_start.py
liblaf/cherries/bundle/__init__.py
liblaf/cherries/bundle/__init__.pyi
liblaf/cherries/bundle/_abc.py
liblaf/cherries/bundle/_landmarks.py
liblaf/cherries/bundle/_registry.py
liblaf/cherries/bundle/_series.py
liblaf/cherries/bundle/_utils.py
liblaf/cherries/config/__init__.py
liblaf/cherries/config/__init__.pyi
liblaf/cherries/config/_config.py
liblaf/cherries/core/__init__.py
liblaf/cherries/core/__init__.pyi
liblaf/cherries/core/_impl.py
liblaf/cherries/core/_methods.py
liblaf/cherries/core/_methods.pyi
liblaf/cherries/core/_plugin.py
liblaf/cherries/core/_plugin_manager.py
liblaf/cherries/core/_plugin_schema.py
liblaf/cherries/core/_run.py
liblaf/cherries/core/_typing.py
liblaf/cherries/meta/__init__.py
liblaf/cherries/meta/__init__.pyi
liblaf/cherries/meta/_git.py
liblaf/cherries/plugins/__init__.py
liblaf/cherries/plugins/__init__.pyi
liblaf/cherries/plugins/comet.py
liblaf/cherries/plugins/git_.py
liblaf/cherries/plugins/local.py
liblaf/cherries/plugins/logging.py
liblaf/cherries/profiles/__init__.py
liblaf/cherries/profiles/__init__.pyi
liblaf/cherries/profiles/_abc.py
liblaf/cherries/profiles/_debug.py
liblaf/cherries/profiles/_default.py
liblaf/cherries/profiles/_factory.py
liblaf_cherries-1.1.0.dist-info/METADATA
liblaf_cherries-1.1.0.dist-info/WHEEL
liblaf_cherries-1.1.0.dist-info/licenses/LICENSE
liblaf_cherries-1.1.0.dist-info/RECORD
