Metadata-Version: 2.4
Name: liblaf-cherries
Version: 1.1.0
Summary: 🍒 Sweet experiment tracking with Comet, DVC, and Git integration.
Project-URL: Changelog, https://github.com/liblaf/cherries/blob/main/CHANGELOG.md
Project-URL: Documentation, https://cherries.readthedocs.io/
Project-URL: Homepage, https://github.com/liblaf/cherries
Project-URL: Issue Tracker, https://github.com/liblaf/cherries/issues
Project-URL: Release Notes, https://github.com/liblaf/cherries/releases
Project-URL: Source Code, https://github.com/liblaf/cherries
Author-email: liblaf <30631553+liblaf@users.noreply.github.com>
License-Expression: MIT
License-File: LICENSE
Classifier: Development Status :: 4 - Beta
Classifier: Intended Audience :: Developers
Classifier: Intended Audience :: Science/Research
Classifier: License :: OSI Approved
Classifier: License :: OSI Approved :: MIT License
Classifier: Operating System :: OS Independent
Classifier: Programming Language :: Python
Classifier: Programming Language :: Python :: 3
Classifier: Programming Language :: Python :: 3.12
Classifier: Programming Language :: Python :: 3.13
Classifier: Programming Language :: Python :: 3.14
Classifier: Topic :: Software Development
Classifier: Topic :: Software Development :: Bug Tracking
Classifier: Topic :: Software Development :: Debuggers
Classifier: Topic :: Software Development :: Libraries
Classifier: Topic :: Software Development :: Libraries :: Python Modules
Classifier: Topic :: System
Classifier: Topic :: System :: Logging
Classifier: Topic :: Utilities
Classifier: Typing :: Typed
Requires-Python: >=3.12
Requires-Dist: attrs<26,>=25
Requires-Dist: cachetools<7,>=6
Requires-Dist: comet-ml<4,>=3
Requires-Dist: dvc[ssh]<4,>=3
Requires-Dist: environs<15,>=14
Requires-Dist: gitpython<4,>=3
Requires-Dist: giturlparse<0.15,>=0.14
Requires-Dist: lazy-loader<0.5,>=0.4
Requires-Dist: liblaf-grapes<10,>=9
Requires-Dist: pydantic-settings<3,>=2
Requires-Dist: pydantic<3,>=2
Requires-Dist: rich<15,>=14
Requires-Dist: wrapt<3,>=2
